AUTHORS.rst
CONTRIBUTING.rst
HISTORY.rst
LICENSE
MANIFEST.in
README.rst
setup.cfg
setup.py
django_fperms.egg-info/PKG-INFO
django_fperms.egg-info/SOURCES.txt
django_fperms.egg-info/dependency_links.txt
django_fperms.egg-info/not-zip-safe
django_fperms.egg-info/requires.txt
django_fperms.egg-info/top_level.txt
fperms/__init__.py
fperms/admin.py
fperms/apps.py
fperms/backends.py
fperms/base.py
fperms/conf.py
fperms/enums.py
fperms/exceptions.py
fperms/managers.py
fperms/models.py
fperms/utils.py
fperms/locale/cs/LC_MESSAGES/django.mo
fperms/locale/cs/LC_MESSAGES/django.po
fperms/migrations/0001_initial.py
fperms/migrations/0002_auto_20180713_1450.py
fperms/migrations/0003_migration.py
fperms/migrations/0004_migration.py
fperms/migrations/0005_migration.py
fperms/migrations/__init__.py
fperms/static/css/django_perms.css
fperms/static/js/django_perms.js
fperms/templates/django_perms/base.html